Workbook

Sheet Overview
B1: SALES AND EXPENSE ANALYSIS USING ADVANCED EXCEL
B4: Project / Case Study | C4: Sales and Expense Analysis using Advanced Excel
B5: Tenure | C5: June – July 2026
B6: Tools Used | C6: MS Excel (Pivot Tables, VLOOKUP, XLOOKUP)
B7: Dataset | C7: 3,000+ sales and expense records, Jan – Dec 2025
B8: Data note | C8: Illustrative sample data generated for this project – replace the Raw_Sales, Raw_Expenses and Products sheets with real data and every sheet updates.
B10: PROJECT OBJECTIVES
B11: 1. Clean and combine 3,000+ sales and expense records using VLOOKUP and XLOOKUP / INDEX-MATCH, removing duplicates and mismatches.
B12: 2. Use pivot tables and charts to track monthly revenue, cost and profit trends and pinpoint the top 5 products by profit.
B14: WORKFLOW – WHAT WAS DONE
B15: Step | C15: Task | D15: Excel feature / formula | E15: Output sheet | F15: Status
B16: 1 | C16: Import raw sales & expense data | D16: Raw_Sales, Raw_Expenses | E16: Raw_Sales | F16: ✔ Done
B17: 2 | C17: Standardise Product IDs | D17: UPPER(), TRIM() | E17: Raw_Sales | F17: ✔ Done
B18: 3 | C18: Detect and remove duplicates | D18: COUNTIF (expanding range) | E18: Raw_Sales / Cleaning_Log | F18: ✔ Done
B19: 4 | C19: Find mismatched / missing IDs | D19: MATCH(), ISNUMBER() | E19: Raw_Sales / Cleaning_Log | F19: ✔ Done
B20: 5 | C20: Join sales with product master | D20: VLOOKUP() | E20: Clean_Data | F20: ✔ Done
B21: 6 | C21: Join sales with expense records | D21: INDEX() + MATCH() (XLOOKUP equivalent) | E21: Clean_Data | F21: ✔ Done
B22: 7 | C22: Calculate Revenue, COGS, Cost, Profit, Margin | D22: Formulas | E22: Clean_Data | F22: ✔ Done
B23: 8 | C23: Monthly revenue, cost & profit trends | D23: SUMIFS() (pivot-style) + chart | E23: Monthly_Analysis | F23: ✔ Done
B24: 9 | C24: Rank products and find Top 5 by profit | D24: SUMIFS(), RANK(), INDEX/MATCH | E24: Product_Analysis | F24: ✔ Done
B25: 10 | C25: Build dashboard with KPIs and charts | D25: Charts, formula-driven insights | E25: Dashboard | F25: ✔ Done
B27: SHEET GUIDE
B28: Dashboard | C28: KPIs, trend chart, Top 5 chart, key insights
B29: Monthly_Analysis | C29: Monthly orders, revenue, cost, profit, margin, MoM growth
B30: Product_Analysis | C30: Profit by product, ranking and Top 5 table
B31: Clean_Data | C31: Final cleaned dataset (Excel Table 'tblSales') – use this for pivot tables
B32: Cleaning_Log | C32: Counts of duplicates, fixes, exclusions and reconciliation
B33: Raw_Sales / Raw_Expenses | C33: Original data as received
B34: Products | C34: Product master with unit cost (blue = editable input)
B36: HOW TO ADD A TRUE PIVOT TABLE
B37: • Clean_Data → click any cell in the table → Insert → PivotTable → New Worksheet.
B38: • Monthly trend: Rows = Month; Values = Revenue, Total Cost, Profit (Sum). Insert → PivotChart.
B39: • Top 5: Rows = Product Name; Values = Profit (Sum); sort Largest to Smallest; Value Filter → Top 10 → set to 5.

Sheet Dashboard
A1: SALES & EXPENSE ANALYSIS DASHBOARD
A3: Jan – Dec 2025 | Source: Clean_Data | Amounts in $
A5: TOTAL REVENUE | C5: TOTAL COST | E5: TOTAL PROFIT | G5: PROFIT MARGIN | I5: ORDERS | K5: AVG ORDER VALUE
A6: =Monthly_Analysis!C18 -> 394207.38 | C6: =Monthly_Analysis!F18 -> 205439.75 | E6: =Monthly_Analysis!G18 -> 188767.63 | G6: =Monthly_Analysis!H18 -> 0.47885362 | I6: =Monthly_Analysis!B18 -> 2985 | K6: =IF(Monthly_Analysis!B18=0,0,Monthly_Analysis!C18/Monthly_Analysis!B18) -> 132.06277
A28: KEY INSIGHTS (auto-generated from the data)
A29: ="• Best profit month: "&TEXT(INDEX(Monthly_Analysis!$A$6:$A$17,MATCH(MAX(Monthly_Analysis!$G$6:$G$17),Monthly_Analysis!$G$6:$G$17,0)),"mmmm yyyy")&" with profit of $"&TEXT(MAX(Monthly_Analysis!$G$6:$G$17),"#,##0")&"." -> • Best profit month: December 2025 with profit of $21,572.
A30: ="• Weakest profit month: "&TEXT(INDEX(Monthly_Analysis!$A$6:$A$17,MATCH(MIN(Monthly_Analysis!$G$6:$G$17),Monthly_Analysis!$G$6:$G$17,0)),"mmmm yyyy")&" with profit of $"&TEXT(MIN(Monthly_Analysis!$G$6:$G$17),"#,##0")&"." -> • Weakest profit month: February 2025 with profit of $9,867.
A31: ="• #1 product by profit: "&Product_Analysis!L6&" ($"&TEXT(Product_Analysis!N6,"#,##0")&", "&TEXT(Product_Analysis!P6,"0.0%")&" of total profit)." -> • #1 product by profit: Office Chair ($23,445, 12.4% of total profit).
A32: ="• The Top 5 products generate "&TEXT(Product_Analysis!P11,"0.0%")&" of total profit." -> • The Top 5 products generate 48.2% of total profit.
A33: ="• Overall profit margin is "&TEXT(Monthly_Analysis!H18,"0.0%")&" on revenue of $"&TEXT(Monthly_Analysis!C18,"#,##0")&"." -> • Overall profit margin is 47.9% on revenue of $394,207.

Sheet Monthly_Analysis
A1: Monthly Revenue, Cost & Profit Trend
A2: SUMIFS summary of Clean_Data by month (pivot-table style). All figures update automatically.
A5: Month | B5: Orders | C5: Revenue | D5: COGS | E5: Operating Expense | F5: Total Cost | G5: Profit | H5: Profit Margin | I5: Revenue MoM %
A6: 45658 | B6: =COUNTIFS(Clean_Data!$J$5:$J$2989,$A6) -> 202 | C6: =SUMIFS(Clean_Data!$K$5:$K$2989,Clean_Data!$J$5:$J$2989,$A6) -> 29209.06 | D6: =SUMIFS(Clean_Data!$L$5:$L$2989,Clean_Data!$J$5:$J$2989,$A6) -> 13576 | E6: =SUMIFS(Clean_Data!$M$5:$M$2989,Clean_Data!$J$5:$J$2989,$A6) -> 1820.04 | F6: =D6+E6 -> 15396.04 | G6: =C6-F6 -> 13813.02 | H6: =IF(C6=0,0,G6/C6) -> 0.4729019
A7: 45689 | B7: =COUNTIFS(Clean_Data!$J$5:$J$2989,$A7) -> 174 | C7: =SUMIFS(Clean_Data!$K$5:$K$2989,Clean_Data!$J$5:$J$2989,$A7) -> 20310.63 | D7: =SUMIFS(Clean_Data!$L$5:$L$2989,Clean_Data!$J$5:$J$2989,$A7) -> 9077 | E7: =SUMIFS(Clean_Data!$M$5:$M$2989,Clean_Data!$J$5:$J$2989,$A7) -> 1366.35 | F7: =D7+E7 -> 10443.35 | G7: =C7-F7 -> 9867.28 | H7: =IF(C7=0,0,G7/C7) -> 0.48581851 | I7: =IF(C6=0,0,C7/C6-1) -> -0.30464623
A8: 45717 | B8: =COUNTIFS(Clean_Data!$J$5:$J$2989,$A8) -> 221 | C8: =SUMIFS(Clean_Data!$K$5:$K$2989,Clean_Data!$J$5:$J$2989,$A8) -> 33633.95 | D8: =SUMIFS(Clean_Data!$L$5:$L$2989,Clean_Data!$J$5:$J$2989,$A8) -> 15595 | E8: =SUMIFS(Clean_Data!$M$5:$M$2989,Clean_Data!$J$5:$J$2989,$A8) -> 2271.56 | F8: =D8+E8 -> 17866.56 | G8: =C8-F8 -> 15767.39 | H8: =IF(C8=0,0,G8/C8) -> 0.46879388 | I8: =IF(C7=0,0,C8/C7-1) -> 0.65597768
A9: 45748 | B9: =COUNTIFS(Clean_Data!$J$5:$J$2989,$A9) -> 226 | C9: =SUMIFS(Clean_Data!$K$5:$K$2989,Clean_Data!$J$5:$J$2989,$A9) -> 27498.26 | D9: =SUMIFS(Clean_Data!$L$5:$L$2989,Clean_Data!$J$5:$J$2989,$A9) -> 12567 | E9: =SUMIFS(Clean_Data!$M$5:$M$2989,Clean_Data!$J$5:$J$2989,$A9) -> 1702.82 | F9: =D9+E9 -> 14269.82 | G9: =C9-F9 -> 13228.44 | H9: =IF(C9=0,0,G9/C9) -> 0.48106462 | I9: =IF(C8=0,0,C9/C8-1) -> -0.1824255
A10: 45778 | B10: =COUNTIFS(Clean_Data!$J$5:$J$2989,$A10) -> 218 | C10: =SUMIFS(Clean_Data!$K$5:$K$2989,Clean_Data!$J$5:$J$2989,$A10) -> 29595.33 | D10: =SUMIFS(Clean_Data!$L$5:$L$2989,Clean_Data!$J$5:$J$2989,$A10) -> 13717 | E10: =SUMIFS(Clean_Data!$M$5:$M$2989,Clean_Data!$J$5:$J$2989,$A10) -> 1889.16 | F10: =D10+E10 -> 15606.16 | G10: =C10-F10 -> 13989.17 | H10: =IF(C10=0,0,G10/C10) -> 0.47268167 | I10: =IF(C9=0,0,C10/C9-1) -> 0.076261916
A11: 45809 | B11: =COUNTIFS(Clean_Data!$J$5:$J$2989,$A11) -> 212 | C11: =SUMIFS(Clean_Data!$K$5:$K$2989,Clean_Data!$J$5:$J$2989,$A11) -> 30965.46 | D11: =SUMIFS(Clean_Data!$L$5:$L$2989,Clean_Data!$J$5:$J$2989,$A11) -> 14234 | E11: =SUMIFS(Clean_Data!$M$5:$M$2989,Clean_Data!$J$5:$J$2989,$A11) -> 1968.89 | F11: =D11+E11 -> 16202.89 | G11: =C11-F11 -> 14762.57 | H11: =IF(C11=0,0,G11/C11) -> 0.47674312 | I11: =IF(C10=0,0,C11/C10-1) -> 0.04629548
A12: 45839 | B12: =COUNTIFS(Clean_Data!$J$5:$J$2989,$A12) -> 231 | C12: =SUMIFS(Clean_Data!$K$5:$K$2989,Clean_Data!$J$5:$J$2989,$A12) -> 31222.43 | D12: =SUMIFS(Clean_Data!$L$5:$L$2989,Clean_Data!$J$5:$J$2989,$A12) -> 14307 | E12: =SUMIFS(Clean_Data!$M$5:$M$2989,Clean_Data!$J$5:$J$2989,$A12) -> 2038.74 | F12: =D12+E12 -> 16345.74 | G12: =C12-F12 -> 14876.69 | H12: =IF(C12=0,0,G12/C12) -> 0.47647444 | I12: =IF(C11=0,0,C12/C11-1) -> 0.0082986011
A13: 45870 | B13: =COUNTIFS(Clean_Data!$J$5:$J$2989,$A13) -> 246 | C13: =SUMIFS(Clean_Data!$K$5:$K$2989,Clean_Data!$J$5:$J$2989,$A13) -> 33224.72 | D13: =SUMIFS(Clean_Data!$L$5:$L$2989,Clean_Data!$J$5:$J$2989,$A13) -> 15252 | E13: =SUMIFS(Clean_Data!$M$5:$M$2989,Clean_Data!$J$5:$J$2989,$A13) -> 2058.54 | F13: =D13+E13 -> 17310.54 | G13: =C13-F13 -> 15914.18 | H13: =IF(C13=0,0,G13/C13) -> 0.47898613 | I13: =IF(C12=0,0,C13/C12-1) -> 0.064129858
A14: 45901 | B14: =COUNTIFS(Clean_Data!$J$5:$J$2989,$A14) -> 275 | C14: =SUMIFS(Clean_Data!$K$5:$K$2989,Clean_Data!$J$5:$J$2989,$A14) -> 34426.33 | D14: =SUMIFS(Clean_Data!$L$5:$L$2989,Clean_Data!$J$5:$J$2989,$A14) -> 15588 | E14: =SUMIFS(Clean_Data!$M$5:$M$2989,Clean_Data!$J$5:$J$2989,$A14) -> 2123.98 | F14: =D14+E14 -> 17711.98 | G14: =C14-F14 -> 16714.35 | H14: =IF(C14=0,0,G14/C14) -> 0.48551065 | I14: =IF(C13=0,0,C14/C13-1) -> 0.036166144
A15: 45931 | B15: =COUNTIFS(Clean_Data!$J$5:$J$2989,$A15) -> 240 | C15: =SUMIFS(Clean_Data!$K$5:$K$2989,Clean_Data!$J$5:$J$2989,$A15) -> 37015.49 | D15: =SUMIFS(Clean_Data!$L$5:$L$2989,Clean_Data!$J$5:$J$2989,$A15) -> 17183 | E15: =SUMIFS(Clean_Data!$M$5:$M$2989,Clean_Data!$J$5:$J$2989,$A15) -> 2409.35 | F15: =D15+E15 -> 19592.35 | G15: =C15-F15 -> 17423.14 | H15: =IF(C15=0,0,G15/C15) -> 0.47069862 | I15: =IF(C14=0,0,C15/C14-1) -> 0.075208714
A16: 45962 | B16: =COUNTIFS(Clean_Data!$J$5:$J$2989,$A16) -> 373 | C16: =SUMIFS(Clean_Data!$K$5:$K$2989,Clean_Data!$J$5:$J$2989,$A16) -> 42870.74 | D16: =SUMIFS(Clean_Data!$L$5:$L$2989,Clean_Data!$J$5:$J$2989,$A16) -> 19277 | E16: =SUMIFS(Clean_Data!$M$5:$M$2989,Clean_Data!$J$5:$J$2989,$A16) -> 2754.07 | F16: =D16+E16 -> 22031.07 | G16: =C16-F16 -> 20839.67 | H16: =IF(C16=0,0,G16/C16) -> 0.48610474 | I16: =IF(C15=0,0,C16/C15-1) -> 0.15818378
A17: 45992 | B17: =COUNTIFS(Clean_Data!$J$5:$J$2989,$A17) -> 367 | C17: =SUMIFS(Clean_Data!$K$5:$K$2989,Clean_Data!$J$5:$J$2989,$A17) -> 44234.98 | D17: =SUMIFS(Clean_Data!$L$5:$L$2989,Clean_Data!$J$5:$J$2989,$A17) -> 19893 | E17: =SUMIFS(Clean_Data!$M$5:$M$2989,Clean_Data!$J$5:$J$2989,$A17) -> 2770.25 | F17: =D17+E17 -> 22663.25 | G17: =C17-F17 -> 21571.73 | H17: =IF(C17=0,0,G17/C17) -> 0.48766225 | I17: =IF(C16=0,0,C17/C16-1) -> 0.031822171
A18: Total | B18: =SUM(B6:B17) -> 2985 | C18: =SUM(C6:C17) -> 394207.38 | D18: =SUM(D6:D17) -> 180266 | E18: =SUM(E6:E17) -> 25173.75 | F18: =SUM(F6:F17) -> 205439.75 | G18: =SUM(G6:G17) -> 188767.63 | H18: =IF(C18=0,0,G18/C18) -> 0.47885362
A19: Note: Revenue = Qty × Unit Price; COGS = Qty × Unit Cost (Products sheet); Operating Expense from Raw_Expenses; Profit = Revenue − COGS − Operating Expense.

Sheet Product_Analysis
A1: Product Profitability & Top 5 Ranking
A2: Profit by product, ranked. Top 5 table (right) is formula-driven from the ranking.
K4: TOP 5 PRODUCTS BY PROFIT
A5: Product ID | B5: Product Name | C5: Category | D5: Units Sold | E5: Revenue | F5: Total Cost | G5: Profit | H5: Profit Margin | I5: Rank | K5: Rank | L5: Product | M5: Revenue | N5: Profit | O5: Profit Margin | P5: % of Total Profit
A6: =Products!A5 -> P001 | B6: =Products!B5 -> Wireless Mouse | C6: =Products!C5 -> Electronics | D6: =SUMIFS(Clean_Data!$D$5:$D$2989,Clean_Data!$C$5:$C$2989,$A6) -> 638 | E6: =SUMIFS(Clean_Data!$K$5:$K$2989,Clean_Data!$C$5:$C$2989,$A6) -> 15280.44 | F6: =SUMIFS(Clean_Data!$N$5:$N$2989,Clean_Data!$C$5:$C$2989,$A6) -> 8645.99 | G6: =E6-F6 -> 6634.45 | H6: =IF(E6=0,0,G6/E6) -> 0.43417925 | I6: =RANK(G6,$G$6:$G$25,0) -> 11 | K6: 1 | L6: =INDEX($B$6:$B$25,MATCH($K6,$I$6:$I$25,0)) -> Office Chair | M6: =INDEX($E$6:$E$25,MATCH($K6,$I$6:$I$25,0)) -> 50296.98 | N6: =INDEX($G$6:$G$25,MATCH($K6,$I$6:$I$25,0)) -> 23444.77 | O6: =INDEX($H$6:$H$25,MATCH($K6,$I$6:$I$25,0)) -> 0.46612679 | P6: =IF($G$26=0,0,N6/$G$26) -> 0.1241991
A7: =Products!A6 -> P002 | B7: =Products!B6 -> Mechanical Keyboard | C7: =Products!C6 -> Electronics | D7: =SUMIFS(Clean_Data!$D$5:$D$2989,Clean_Data!$C$5:$C$2989,$A7) -> 358 | E7: =SUMIFS(Clean_Data!$K$5:$K$2989,Clean_Data!$C$5:$C$2989,$A7) -> 27174.12 | F7: =SUMIFS(Clean_Data!$N$5:$N$2989,Clean_Data!$C$5:$C$2989,$A7) -> 15374.08 | G7: =E7-F7 -> 11800.04 | H7: =IF(E7=0,0,G7/E7) -> 0.43423816 | I7: =RANK(G7,$G$6:$G$25,0) -> 7 | K7: 2 | L7: =INDEX($B$6:$B$25,MATCH($K7,$I$6:$I$25,0)) -> Standing Desk | M7: =INDEX($E$6:$E$25,MATCH($K7,$I$6:$I$25,0)) -> 45186.33 | N7: =INDEX($G$6:$G$25,MATCH($K7,$I$6:$I$25,0)) -> 20954.41 | O7: =INDEX($H$6:$H$25,MATCH($K7,$I$6:$I$25,0)) -> 0.46373339 | P7: =IF($G$26=0,0,N7/$G$26) -> 0.11100637
A8: =Products!A7 -> P003 | B8: =Products!B7 -> USB-C Hub | C8: =Products!C7 -> Electronics | D8: =SUMIFS(Clean_Data!$D$5:$D$2989,Clean_Data!$C$5:$C$2989,$A8) -> 375 | E8: =SUMIFS(Clean_Data!$K$5:$K$2989,Clean_Data!$C$5:$C$2989,$A8) -> 12633.14 | F8: =SUMIFS(Clean_Data!$N$5:$N$2989,Clean_Data!$C$5:$C$2989,$A8) -> 6053.21 | G8: =E8-F8 -> 6579.93 | H8: =IF(E8=0,0,G8/E8) -> 0.52084676 | I8: =RANK(G8,$G$6:$G$25,0) -> 12 | K8: 3 | L8: =INDEX($B$6:$B$25,MATCH($K8,$I$6:$I$25,0)) -> Noise-Cancelling Headphones | M8: =INDEX($E$6:$E$25,MATCH($K8,$I$6:$I$25,0)) -> 40554.19 | N8: =INDEX($G$6:$G$25,MATCH($K8,$I$6:$I$25,0)) -> 19850.6 | O8: =INDEX($H$6:$H$25,MATCH($K8,$I$6:$I$25,0)) -> 0.48948333 | P8: =IF($G$26=0,0,N8/$G$26) -> 0.10515892
A9: =Products!A8 -> P004 | B9: =Products!B8 -> Laptop Stand | C9: =Products!C8 -> Accessories | D9: =SUMIFS(Clean_Data!$D$5:$D$2989,Clean_Data!$C$5:$C$2989,$A9) -> 400 | E9: =SUMIFS(Clean_Data!$K$5:$K$2989,Clean_Data!$C$5:$C$2989,$A9) -> 11186.64 | F9: =SUMIFS(Clean_Data!$N$5:$N$2989,Clean_Data!$C$5:$C$2989,$A9) -> 5100.53 | G9: =E9-F9 -> 6086.11 | H9: =IF(E9=0,0,G9/E9) -> 0.54405165 | I9: =RANK(G9,$G$6:$G$25,0) -> 13 | K9: 4 | L9: =INDEX($B$6:$B$25,MATCH($K9,$I$6:$I$25,0)) -> 24-inch Monitor | M9: =INDEX($E$6:$E$25,MATCH($K9,$I$6:$I$25,0)) -> 32295.49 | N9: =INDEX($G$6:$G$25,MATCH($K9,$I$6:$I$25,0)) -> 13408.59 | O9: =INDEX($H$6:$H$25,MATCH($K9,$I$6:$I$25,0)) -> 0.4151846 | P9: =IF($G$26=0,0,N9/$G$26) -> 0.071032253
A10: =Products!A9 -> P005 | B10: =Products!B9 -> HD Webcam | C10: =Products!C9 -> Electronics | D10: =SUMIFS(Clean_Data!$D$5:$D$2989,Clean_Data!$C$5:$C$2989,$A10) -> 379 | E10: =SUMIFS(Clean_Data!$K$5:$K$2989,Clean_Data!$C$5:$C$2989,$A10) -> 20020.22 | F10: =SUMIFS(Clean_Data!$N$5:$N$2989,Clean_Data!$C$5:$C$2989,$A10) -> 9623.05 | G10: =E10-F10 -> 10397.17 | H10: =IF(E10=0,0,G10/E10) -> 0.51933345 | I10: =RANK(G10,$G$6:$G$25,0) -> 8 | K10: 5 | L10: =INDEX($B$6:$B$25,MATCH($K10,$I$6:$I$25,0)) -> External SSD 1TB | M10: =INDEX($E$6:$E$25,MATCH($K10,$I$6:$I$25,0)) -> 33962.29 | N10: =INDEX($G$6:$G$25,MATCH($K10,$I$6:$I$25,0)) -> 13366.46 | O10: =INDEX($H$6:$H$25,MATCH($K10,$I$6:$I$25,0)) -> 0.39356769 | P10: =IF($G$26=0,0,N10/$G$26) -> 0.070809068
A11: =Products!A10 -> P006 | B11: =Products!B10 -> Noise-Cancelling Headphones | C11: =Products!C10 -> Electronics | D11: =SUMIFS(Clean_Data!$D$5:$D$2989,Clean_Data!$C$5:$C$2989,$A11) -> 327 | E11: =SUMIFS(Clean_Data!$K$5:$K$2989,Clean_Data!$C$5:$C$2989,$A11) -> 40554.19 | F11: =SUMIFS(Clean_Data!$N$5:$N$2989,Clean_Data!$C$5:$C$2989,$A11) -> 20703.59 | G11: =E11-F11 -> 19850.6 | H11: =IF(E11=0,0,G11/E11) -> 0.48948333 | I11: =RANK(G11,$G$6:$G$25,0) -> 3 | L11: Top 5 combined | N11: =SUM(N6:N10) -> 91024.83 | P11: =SUM(P6:P10) -> 0.48220572
A12: =Products!A11 -> P007 | B12: =Products!B11 -> Office Chair | C12: =Products!C11 -> Furniture | D12: =SUMIFS(Clean_Data!$D$5:$D$2989,Clean_Data!$C$5:$C$2989,$A12) -> 277 | E12: =SUMIFS(Clean_Data!$K$5:$K$2989,Clean_Data!$C$5:$C$2989,$A12) -> 50296.98 | F12: =SUMIFS(Clean_Data!$N$5:$N$2989,Clean_Data!$C$5:$C$2989,$A12) -> 26852.21 | G12: =E12-F12 -> 23444.77 | H12: =IF(E12=0,0,G12/E12) -> 0.46612679 | I12: =RANK(G12,$G$6:$G$25,0) -> 1
A13: =Products!A12 -> P008 | B13: =Products!B12 -> Standing Desk | C13: =Products!C12 -> Furniture | D13: =SUMIFS(Clean_Data!$D$5:$D$2989,Clean_Data!$C$5:$C$2989,$A13) -> 134 | E13: =SUMIFS(Clean_Data!$K$5:$K$2989,Clean_Data!$C$5:$C$2989,$A13) -> 45186.33 | F13: =SUMIFS(Clean_Data!$N$5:$N$2989,Clean_Data!$C$5:$C$2989,$A13) -> 24231.92 | G13: =E13-F13 -> 20954.41 | H13: =IF(E13=0,0,G13/E13) -> 0.46373339 | I13: =RANK(G13,$G$6:$G$25,0) -> 2
A14: =Products!A13 -> P009 | B14: =Products!B13 -> Desk Lamp | C14: =Products!C13 -> Furniture | D14: =SUMIFS(Clean_Data!$D$5:$D$2989,Clean_Data!$C$5:$C$2989,$A14) -> 440 | E14: =SUMIFS(Clean_Data!$K$5:$K$2989,Clean_Data!$C$5:$C$2989,$A14) -> 13538.45 | F14: =SUMIFS(Clean_Data!$N$5:$N$2989,Clean_Data!$C$5:$C$2989,$A14) -> 6561.6 | G14: =E14-F14 -> 6976.85 | H14: =IF(E14=0,0,G14/E14) -> 0.51533595 | I14: =RANK(G14,$G$6:$G$25,0) -> 10
A15: =Products!A14 -> P010 | B15: =Products!B14 -> 24-inch Monitor | C15: =Products!C14 -> Electronics | D15: =SUMIFS(Clean_Data!$D$5:$D$2989,Clean_Data!$C$5:$C$2989,$A15) -> 188 | E15: =SUMIFS(Clean_Data!$K$5:$K$2989,Clean_Data!$C$5:$C$2989,$A15) -> 32295.49 | F15: =SUMIFS(Clean_Data!$N$5:$N$2989,Clean_Data!$C$5:$C$2989,$A15) -> 18886.9 | G15: =E15-F15 -> 13408.59 | H15: =IF(E15=0,0,G15/E15) -> 0.4151846 | I15: =RANK(G15,$G$6:$G$25,0) -> 4
A16: =Products!A15 -> P011 | B16: =Products!B15 -> Notebook Set | C16: =Products!C15 -> Stationery | D16: =SUMIFS(Clean_Data!$D$5:$D$2989,Clean_Data!$C$5:$C$2989,$A16) -> 658 | E16: =SUMIFS(Clean_Data!$K$5:$K$2989,Clean_Data!$C$5:$C$2989,$A16) -> 5683.53 | F16: =SUMIFS(Clean_Data!$N$5:$N$2989,Clean_Data!$C$5:$C$2989,$A16) -> 2334.63 | G16: =E16-F16 -> 3348.9 | H16: =IF(E16=0,0,G16/E16) -> 0.58922888 | I16: =RANK(G16,$G$6:$G$25,0) -> 18
A17: =Products!A16 -> P012 | B17: =Products!B16 -> Gel Pen Pack | C17: =Products!C16 -> Stationery | D17: =SUMIFS(Clean_Data!$D$5:$D$2989,Clean_Data!$C$5:$C$2989,$A17) -> 721 | E17: =SUMIFS(Clean_Data!$K$5:$K$2989,Clean_Data!$C$5:$C$2989,$A17) -> 4143.88 | F17: =SUMIFS(Clean_Data!$N$5:$N$2989,Clean_Data!$C$5:$C$2989,$A17) -> 1705.26 | G17: =E17-F17 -> 2438.62 | H17: =IF(E17=0,0,G17/E17) -> 0.58848712 | I17: =RANK(G17,$G$6:$G$25,0) -> 19
A18: =Products!A17 -> P013 | B18: =Products!B17 -> Whiteboard | C18: =Products!C17 -> Furniture | D18: =SUMIFS(Clean_Data!$D$5:$D$2989,Clean_Data!$C$5:$C$2989,$A18) -> 198 | E18: =SUMIFS(Clean_Data!$K$5:$K$2989,Clean_Data!$C$5:$C$2989,$A18) -> 11195.76 | F18: =SUMIFS(Clean_Data!$N$5:$N$2989,Clean_Data!$C$5:$C$2989,$A18) -> 6237.89 | G18: =E18-F18 -> 4957.87 | H18: =IF(E18=0,0,G18/E18) -> 0.44283461 | I18: =RANK(G18,$G$6:$G$25,0) -> 15
A19: =Products!A18 -> P014 | B19: =Products!B18 -> Backpack | C19: =Products!C18 -> Accessories | D19: =SUMIFS(Clean_Data!$D$5:$D$2989,Clean_Data!$C$5:$C$2989,$A19) -> 415 | E19: =SUMIFS(Clean_Data!$K$5:$K$2989,Clean_Data!$C$5:$C$2989,$A19) -> 17904.07 | F19: =SUMIFS(Clean_Data!$N$5:$N$2989,Clean_Data!$C$5:$C$2989,$A19) -> 8164.5 | G19: =E19-F19 -> 9739.57 | H19: =IF(E19=0,0,G19/E19) -> 0.54398637 | I19: =RANK(G19,$G$6:$G$25,0) -> 9
A20: =Products!A19 -> P015 | B20: =Products!B19 -> Water Bottle | C20: =Products!C19 -> Accessories | D20: =SUMIFS(Clean_Data!$D$5:$D$2989,Clean_Data!$C$5:$C$2989,$A20) -> 521 | E20: =SUMIFS(Clean_Data!$K$5:$K$2989,Clean_Data!$C$5:$C$2989,$A20) -> 8007.47 | F20: =SUMIFS(Clean_Data!$N$5:$N$2989,Clean_Data!$C$5:$C$2989,$A20) -> 3132.54 | G20: =E20-F20 -> 4874.93 | H20: =IF(E20=0,0,G20/E20) -> 0.60879779 | I20: =RANK(G20,$G$6:$G$25,0) -> 16
A21: =Products!A20 -> P016 | B21: =Products!B20 -> Phone Stand | C21: =Products!C20 -> Accessories | D21: =SUMIFS(Clean_Data!$D$5:$D$2989,Clean_Data!$C$5:$C$2989,$A21) -> 450 | E21: =SUMIFS(Clean_Data!$K$5:$K$2989,Clean_Data!$C$5:$C$2989,$A21) -> 6035.88 | F21: =SUMIFS(Clean_Data!$N$5:$N$2989,Clean_Data!$C$5:$C$2989,$A21) -> 2199.12 | G21: =E21-F21 -> 3836.76 | H21: =IF(E21=0,0,G21/E21) -> 0.63565876 | I21: =RANK(G21,$G$6:$G$25,0) -> 17
A22: =Products!A21 -> P017 | B22: =Products!B21 -> Bluetooth Speaker | C22: =Products!C21 -> Electronics | D22: =SUMIFS(Clean_Data!$D$5:$D$2989,Clean_Data!$C$5:$C$2989,$A22) -> 374 | E22: =SUMIFS(Clean_Data!$K$5:$K$2989,Clean_Data!$C$5:$C$2989,$A22) -> 24723.6 | F22: =SUMIFS(Clean_Data!$N$5:$N$2989,Clean_Data!$C$5:$C$2989,$A22) -> 12080.32 | G22: =E22-F22 -> 12643.28 | H22: =IF(E22=0,0,G22/E22) -> 0.51138507 | I22: =RANK(G22,$G$6:$G$25,0) -> 6
A23: =Products!A22 -> P018 | B23: =Products!B22 -> External SSD 1TB | C23: =Products!C22 -> Electronics | D23: =SUMIFS(Clean_Data!$D$5:$D$2989,Clean_Data!$C$5:$C$2989,$A23) -> 298 | E23: =SUMIFS(Clean_Data!$K$5:$K$2989,Clean_Data!$C$5:$C$2989,$A23) -> 33962.29 | F23: =SUMIFS(Clean_Data!$N$5:$N$2989,Clean_Data!$C$5:$C$2989,$A23) -> 20595.83 | G23: =E23-F23 -> 13366.46 | H23: =IF(E23=0,0,G23/E23) -> 0.39356769 | I23: =RANK(G23,$G$6:$G$25,0) -> 5
... A25: =Products!A24 -> P020 | B25: =Products!B24 -> Ergonomic Footrest | C25: =Products!C24 -> Furniture | D25: =SUMIFS(Clean_Data!$D$5:$D$2989,Clean_Data!$C$5:$C$2989,$A25) -> 264 | E25: =SUMIFS(Clean_Data!$K$5:$K$2989,Clean_Data!$C$5:$C$2989,$A25) -> 9888.89 | F25: =SUMIFS(Clean_Data!$N$5:$N$2989,Clean_Data!$C$5:$C$2989,$A25) -> 4584.44 | G25: =E25-F25 -> 5304.45 | H25: =IF(E25=0,0,G25/E25) -> 0.536405 | I25: =RANK(G25,$G$6:$G$25,0) -> 14
A26: Total | D26: =SUM(D6:D25) -> 7935 | E26: =SUM(E6:E25) -> 394207.38 | F26: =SUM(F6:F25) -> 205439.75 | G26: =SUM(G6:G25) -> 188767.63 | H26: =IF(E26=0,0,G26/E26) -> 0.47885362

Sheet Clean_Data
A1: Clean Combined Dataset
A2: Duplicates removed, IDs standardised, sales joined to product master (VLOOKUP) and expenses (INDEX/MATCH). Source for pivot tables.
A4: Order ID | B4: Order Date | C4: Product ID | D4: Qty | E4: Unit Price | F4: Region | G4: Product Name | H4: Category | I4: Unit Cost | J4: Month | K4: Revenue | L4: COGS | M4: Operating Expense | N4: Total Cost | O4: Profit | P4: Profit Margin
A5: ORD-10001 | B5: 45658 | C5: P015 | D5: 3 | E5: 15.73 | F5: North | G5: =VLOOKUP(C5,Products!$A$5:$D$24,2,FALSE()) -> Water Bottle | H5: =VLOOKUP(C5,Products!$A$5:$D$24,3,FALSE()) -> Accessories | I5: =VLOOKUP(C5,Products!$A$5:$D$24,4,FALSE()) -> 5 | J5: =DATE(YEAR(B5),MONTH(B5),1) -> 45658 | K5: =D5*E5 -> 47.19 | L5: =D5*I5 -> 15 | M5: =IFERROR(INDEX(Raw_Expenses!$C$5:$C$2979,MATCH(A5,Raw_Expenses!$A$5:$A$2979,0)),0) -> 1.93 | N5: =L5+M5 -> 16.93 | O5: =K5-N5 -> 30.26 | P5: =IF(K5=0,0,O5/K5) -> 0.64123755
A6: ORD-10002 | B6: 45658 | C6: P003 | D6: 3 | E6: 32.29 | F6: East | G6: =VLOOKUP(C6,Products!$A$5:$D$24,2,FALSE()) -> USB-C Hub | H6: =VLOOKUP(C6,Products!$A$5:$D$24,3,FALSE()) -> Electronics | I6: =VLOOKUP(C6,Products!$A$5:$D$24,4,FALSE()) -> 14 | J6: =DATE(YEAR(B6),MONTH(B6),1) -> 45658 | K6: =D6*E6 -> 96.87 | L6: =D6*I6 -> 42 | M6: =IFERROR(INDEX(Raw_Expenses!$C$5:$C$2979,MATCH(A6,Raw_Expenses!$A$5:$A$2979,0)),0) -> 7.9 | N6: =L6+M6 -> 49.9 | O6: =K6-N6 -> 46.97 | P6: =IF(K6=0,0,O6/K6) -> 0.48487664
A7: ORD-10003 | B7: 45658 | C7: P016 | D7: 5 | E7: 13.36 | F7: North | G7: =VLOOKUP(C7,Products!$A$5:$D$24,2,FALSE()) -> Phone Stand | H7: =VLOOKUP(C7,Products!$A$5:$D$24,3,FALSE()) -> Accessories | I7: =VLOOKUP(C7,Products!$A$5:$D$24,4,FALSE()) -> 4 | J7: =DATE(YEAR(B7),MONTH(B7),1) -> 45658 | K7: =D7*E7 -> 66.8 | L7: =D7*I7 -> 20 | M7: =IFERROR(INDEX(Raw_Expenses!$C$5:$C$2979,MATCH(A7,Raw_Expenses!$A$5:$A$2979,0)),0) -> 4.1 | N7: =L7+M7 -> 24.1 | O7: =K7-N7 -> 42.7 | P7: =IF(K7=0,0,O7/K7) -> 0.63922156
A8: ORD-10004 | B8: 45658 | C8: P005 | D8: 2 | E8: 54.82 | F8: North | G8: =VLOOKUP(C8,Products!$A$5:$D$24,2,FALSE()) -> HD Webcam | H8: =VLOOKUP(C8,Products!$A$5:$D$24,3,FALSE()) -> Electronics | I8: =VLOOKUP(C8,Products!$A$5:$D$24,4,FALSE()) -> 22 | J8: =DATE(YEAR(B8),MONTH(B8),1) -> 45658 | K8: =D8*E8 -> 109.64 | L8: =D8*I8 -> 44 | M8: =IFERROR(INDEX(Raw_Expenses!$C$5:$C$2979,MATCH(A8,Raw_Expenses!$A$5:$A$2979,0)),0) -> 7.06 | N8: =L8+M8 -> 51.06 | O8: =K8-N8 -> 58.58 | P8: =IF(K8=0,0,O8/K8) -> 0.53429405
A9: ORD-10005 | B9: 45658 | C9: P012 | D9: 2 | E9: 5.91 | F9: West | G9: =VLOOKUP(C9,Products!$A$5:$D$24,2,FALSE()) -> Gel Pen Pack | H9: =VLOOKUP(C9,Products!$A$5:$D$24,3,FALSE()) -> Stationery | I9: =VLOOKUP(C9,Products!$A$5:$D$24,4,FALSE()) -> 2 | J9: =DATE(YEAR(B9),MONTH(B9),1) -> 45658 | K9: =D9*E9 -> 11.82 | L9: =D9*I9 -> 4 | M9: =IFERROR(INDEX(Raw_Expenses!$C$5:$C$2979,MATCH(A9,Raw_Expenses!$A$5:$A$2979,0)),0) -> 0.49 | N9: =L9+M9 -> 4.49 | O9: =K9-N9 -> 7.33 | P9: =IF(K9=0,0,O9/K9) -> 0.62013536
A10: ORD-10006 | B10: 45658 | C10: P009 | D10: 4 | E10: 29.73 | F10: South | G10: =VLOOKUP(C10,Products!$A$5:$D$24,2,FALSE()) -> Desk Lamp | H10: =VLOOKUP(C10,Products!$A$5:$D$24,3,FALSE()) -> Furniture | I10: =VLOOKUP(C10,Products!$A$5:$D$24,4,FALSE()) -> 13 | J10: =DATE(YEAR(B10),MONTH(B10),1) -> 45658 | K10: =D10*E10 -> 118.92 | L10: =D10*I10 -> 52 | M10: =IFERROR(INDEX(Raw_Expenses!$C$5:$C$2979,MATCH(A10,Raw_Expenses!$A$5:$A$2979,0)),0) -> 9.63 | N10: =L10+M10 -> 61.63 | O10: =K10-N10 -> 57.29 | P10: =IF(K10=0,0,O10/K10) -> 0.48175244
A11: ORD-10007 | B11: 45658 | C11: P009 | D11: 1 | E11: 30.8 | F11: North | G11: =VLOOKUP(C11,Products!$A$5:$D$24,2,FALSE()) -> Desk Lamp | H11: =VLOOKUP(C11,Products!$A$5:$D$24,3,FALSE()) -> Furniture | I11: =VLOOKUP(C11,Products!$A$5:$D$24,4,FALSE()) -> 13 | J11: =DATE(YEAR(B11),MONTH(B11),1) -> 45658 | K11: =D11*E11 -> 30.8 | L11: =D11*I11 -> 13 | M11: =IFERROR(INDEX(Raw_Expenses!$C$5:$C$2979,MATCH(A11,Raw_Expenses!$A$5:$A$2979,0)),0) -> 2.2 | N11: =L11+M11 -> 15.2 | O11: =K11-N11 -> 15.6 | P11: =IF(K11=0,0,O11/K11) -> 0.50649351
A12: ORD-10008 | B12: 45659 | C12: P018 | D12: 2 | E12: 115.64 | F12: West | G12: =VLOOKUP(C12,Products!$A$5:$D$24,2,FALSE()) -> External SSD 1TB | H12: =VLOOKUP(C12,Products!$A$5:$D$24,3,FALSE()) -> Electronics | I12: =VLOOKUP(C12,Products!$A$5:$D$24,4,FALSE()) -> 62 | J12: =DATE(YEAR(B12),MONTH(B12),1) -> 45658 | K12: =D12*E12 -> 231.28 | L12: =D12*I12 -> 124 | M12: =IFERROR(INDEX(Raw_Expenses!$C$5:$C$2979,MATCH(A12,Raw_Expenses!$A$5:$A$2979,0)),0) -> 17.45 | N12: =L12+M12 -> 141.45 | O12: =K12-N12 -> 89.83 | P12: =IF(K12=0,0,O12/K12) -> 0.38840367
A13: ORD-10009 | B13: 45659 | C13: P015 | D13: 1 | E13: 15.92 | F13: East | G13: =VLOOKUP(C13,Products!$A$5:$D$24,2,FALSE()) -> Water Bottle | H13: =VLOOKUP(C13,Products!$A$5:$D$24,3,FALSE()) -> Accessories | I13: =VLOOKUP(C13,Products!$A$5:$D$24,4,FALSE()) -> 5 | J13: =DATE(YEAR(B13),MONTH(B13),1) -> 45658 | K13: =D13*E13 -> 15.92 | L13: =D13*I13 -> 5 | M13: =IFERROR(INDEX(Raw_Expenses!$C$5:$C$2979,MATCH(A13,Raw_Expenses!$A$5:$A$2979,0)),0) -> 1.41 | N13: =L13+M13 -> 6.41 | O13: =K13-N13 -> 9.51 | P13: =IF(K13=0,0,O13/K13) -> 0.59736181
A14: ORD-10010 | B14: 45659 | C14: P016 | D14: 2 | E14: 13.66 | F14: South | G14: =VLOOKUP(C14,Products!$A$5:$D$24,2,FALSE()) -> Phone Stand | H14: =VLOOKUP(C14,Products!$A$5:$D$24,3,FALSE()) -> Accessories | I14: =VLOOKUP(C14,Products!$A$5:$D$24,4,FALSE()) -> 4 | J14: =DATE(YEAR(B14),MONTH(B14),1) -> 45658 | K14: =D14*E14 -> 27.32 | L14: =D14*I14 -> 8 | M14: =IFERROR(INDEX(Raw_Expenses!$C$5:$C$2979,MATCH(A14,Raw_Expenses!$A$5:$A$2979,0)),0) -> 1.19 | N14: =L14+M14 -> 9.19 | O14: =K14-N14 -> 18.13 | P14: =IF(K14=0,0,O14/K14) -> 0.6636164
A15: ORD-10011 | B15: 45660 | C15: P003 | D15: 1 | E15: 34.04 | F15: West | G15: =VLOOKUP(C15,Products!$A$5:$D$24,2,FALSE()) -> USB-C Hub | H15: =VLOOKUP(C15,Products!$A$5:$D$24,3,FALSE()) -> Electronics | I15: =VLOOKUP(C15,Products!$A$5:$D$24,4,FALSE()) -> 14 | J15: =DATE(YEAR(B15),MONTH(B15),1) -> 45658 | K15: =D15*E15 -> 34.04 | L15: =D15*I15 -> 14 | M15: =IFERROR(INDEX(Raw_Expenses!$C$5:$C$2979,MATCH(A15,Raw_Expenses!$A$5:$A$2979,0)),0) -> 2.36 | N15: =L15+M15 -> 16.36 | O15: =K15-N15 -> 17.68 | P15: =IF(K15=0,0,O15/K15) -> 0.51938895
A16: ORD-10012 | B16: 45660 | C16: P001 | D16: 1 | E16: 23.2 | F16: South | G16: =VLOOKUP(C16,Products!$A$5:$D$24,2,FALSE()) -> Wireless Mouse | H16: =VLOOKUP(C16,Products!$A$5:$D$24,3,FALSE()) -> Electronics | I16: =VLOOKUP(C16,Products!$A$5:$D$24,4,FALSE()) -> 12 | J16: =DATE(YEAR(B16),MONTH(B16),1) -> 45658 | K16: =D16*E16 -> 23.2 | L16: =D16*I16 -> 12 | M16: =IFERROR(INDEX(Raw_Expenses!$C$5:$C$2979,MATCH(A16,Raw_Expenses!$A$5:$A$2979,0)),0) -> 1.9 | N16: =L16+M16 -> 13.9 | O16: =K16-N16 -> 9.3 | P16: =IF(K16=0,0,O16/K16) -> 0.40086207
... A2989: ORD-13000 | B2989: 46019 | C2989: P011 | D2989: 2 | E2989: 8.91 | F2989: South | G2989: =VLOOKUP(C2989,Products!$A$5:$D$24,2,FALSE()) -> Notebook Set | H2989: =VLOOKUP(C2989,Products!$A$5:$D$24,3,FALSE()) -> Stationery | I2989: =VLOOKUP(C2989,Products!$A$5:$D$24,4,FALSE()) -> 3 | J2989: =DATE(YEAR(B2989),MONTH(B2989),1) -> 45992 | K2989: =D2989*E2989 -> 17.82 | L2989: =D2989*I2989 -> 6 | M2989: =IFERROR(INDEX(Raw_Expenses!$C$5:$C$2979,MATCH(A2989,Raw_Expenses!$A$5:$A$2979,0)),0) -> 1.42 | N2989: =L2989+M2989 -> 7.42 | O2989: =K2989-N2989 -> 10.4 | P2989: =IF(K2989=0,0,O2989/K2989) -> 0.58361392

Sheet Cleaning_Log
A1: Data Cleaning & Validation Log
A2: Every figure is a live formula on the raw and clean sheets.
A4: Check | B4: Result | C4: What it means / action taken
A5: Raw sales records received | B5: =COUNTA(Raw_Sales!$A$5:$A$3074) -> 3070 | C5: Rows in the original sales export
A6: Duplicate records | B6: =COUNTIF(Raw_Sales!$I$5:$I$3074,"Duplicate") -> 70 | C6: Same Order ID repeated – later copies removed
A7: Product IDs needing formatting fix | B7: =SUMPRODUCT(--NOT(EXACT(Raw_Sales!$C$5:$C$3074,Raw_Sales!$G$5:$G$3074))) -> 52 | C7: Extra spaces / lowercase – fixed with UPPER(TRIM())
A8: Unmatched Product IDs (non-duplicate) | B8: =COUNTIF(Raw_Sales!$J$5:$J$3074,"Exclude") -> 15 | C8: ID not found in Product master – excluded and flagged for follow-up
A9: Records kept for analysis | B9: =COUNTIF(Raw_Sales!$J$5:$J$3074,"Keep") -> 2985 | C9: Unique, matched records
A10: Records in Clean_Data sheet | B10: =COUNTA(Clean_Data!$A$5:$A$2989) -> 2985 | C10: Should equal 'Records kept'
A11: Reconciliation check | B11: =IF(B9=B10,"OK – counts agree","CHECK – counts differ") -> OK – counts agree | C11: Clean_Data vs. Raw_Sales 'Keep' rows
A12: Orders with no expense record | B12: =SUMPRODUCT(--ISNA(MATCH(Clean_Data!$A$5:$A$2989,Raw_Expenses!$A$5:$A$2979,0))) -> 25 | C12: Operating expense treated as 0 – verify with finance
A13: Total raw expense records | B13: =COUNTA(Raw_Expenses!$A$5:$A$2979) -> 2975 | C13: Expense rows received
A15: Cleaning steps applied
A16: 1. Standardised Product IDs with UPPER(TRIM()) to remove spaces and case differences.
A17: 2. Flagged duplicates with an expanding COUNTIF on Order ID; only the first occurrence is kept.
A18: 3. Validated each Product ID against the Product master with MATCH; unmatched IDs excluded.
A19: 4. Combined sales with product details using VLOOKUP and with expenses using INDEX/MATCH (the classic equivalent of XLOOKUP).
A20: 5. Reconciled record counts between Raw_Sales and Clean_Data.

Sheet Raw_Sales
A1: Raw Sales Records (as received)
A2: Columns A–F are the raw export. Columns G–J are cleaning checks driven by formulas.
A4: Order ID | B4: Order Date | C4: Product ID (raw) | D4: Qty | E4: Unit Price | F4: Region | G4: Product ID (clean) | H4: Product Match? | I4: Duplicate? | J4: Action
A5: ORD-10001 | B5: 45658 | C5: P015 | D5: 3 | E5: 15.73 | F5: North | G5: =UPPER(TRIM(C5)) -> P015 | H5: =IF(ISNUMBER(MATCH(G5,Products!$A$5:$A$24,0)),"OK","Mismatch") -> OK | I5: =IF(COUNTIF($A$5:A5,A5)>1,"Duplicate","Unique") -> Unique | J5: =IF(I5="Duplicate","Remove",IF(H5="Mismatch","Exclude","Keep")) -> Keep
A6: ORD-10002 | B6: 45658 | C6: P003 | D6: 3 | E6: 32.29 | F6: East | G6: =UPPER(TRIM(C6)) -> P003 | H6: =IF(ISNUMBER(MATCH(G6,Products!$A$5:$A$24,0)),"OK","Mismatch") -> OK | I6: =IF(COUNTIF($A$5:A6,A6)>1,"Duplicate","Unique") -> Unique | J6: =IF(I6="Duplicate","Remove",IF(H6="Mismatch","Exclude","Keep")) -> Keep
A7: ORD-10003 | B7: 45658 | C7: P016 | D7: 5 | E7: 13.36 | F7: North | G7: =UPPER(TRIM(C7)) -> P016 | H7: =IF(ISNUMBER(MATCH(G7,Products!$A$5:$A$24,0)),"OK","Mismatch") -> OK | I7: =IF(COUNTIF($A$5:A7,A7)>1,"Duplicate","Unique") -> Unique | J7: =IF(I7="Duplicate","Remove",IF(H7="Mismatch","Exclude","Keep")) -> Keep
A8: ORD-10004 | B8: 45658 | C8: P005 | D8: 2 | E8: 54.82 | F8: North | G8: =UPPER(TRIM(C8)) -> P005 | H8: =IF(ISNUMBER(MATCH(G8,Products!$A$5:$A$24,0)),"OK","Mismatch") -> OK | I8: =IF(COUNTIF($A$5:A8,A8)>1,"Duplicate","Unique") -> Unique | J8: =IF(I8="Duplicate","Remove",IF(H8="Mismatch","Exclude","Keep")) -> Keep
A9: ORD-10005 | B9: 45658 | C9: P012 | D9: 2 | E9: 5.91 | F9: West | G9: =UPPER(TRIM(C9)) -> P012 | H9: =IF(ISNUMBER(MATCH(G9,Products!$A$5:$A$24,0)),"OK","Mismatch") -> OK | I9: =IF(COUNTIF($A$5:A9,A9)>1,"Duplicate","Unique") -> Unique | J9: =IF(I9="Duplicate","Remove",IF(H9="Mismatch","Exclude","Keep")) -> Keep
A10: ORD-10006 | B10: 45658 | C10: P009 | D10: 4 | E10: 29.73 | F10: South | G10: =UPPER(TRIM(C10)) -> P009 | H10: =IF(ISNUMBER(MATCH(G10,Products!$A$5:$A$24,0)),"OK","Mismatch") -> OK | I10: =IF(COUNTIF($A$5:A10,A10)>1,"Duplicate","Unique") -> Unique | J10: =IF(I10="Duplicate","Remove",IF(H10="Mismatch","Exclude","Keep")) -> Keep
A11: ORD-10007 | B11: 45658 | C11: P009 | D11: 1 | E11: 30.8 | F11: North | G11: =UPPER(TRIM(C11)) -> P009 | H11: =IF(ISNUMBER(MATCH(G11,Products!$A$5:$A$24,0)),"OK","Mismatch") -> OK | I11: =IF(COUNTIF($A$5:A11,A11)>1,"Duplicate","Unique") -> Unique | J11: =IF(I11="Duplicate","Remove",IF(H11="Mismatch","Exclude","Keep")) -> Keep
A12: ORD-10008 | B12: 45659 | C12: P018 | D12: 2 | E12: 115.64 | F12: West | G12: =UPPER(TRIM(C12)) -> P018 | H12: =IF(ISNUMBER(MATCH(G12,Products!$A$5:$A$24,0)),"OK","Mismatch") -> OK | I12: =IF(COUNTIF($A$5:A12,A12)>1,"Duplicate","Unique") -> Unique | J12: =IF(I12="Duplicate","Remove",IF(H12="Mismatch","Exclude","Keep")) -> Keep
A13: ORD-10009 | B13: 45659 | C13: P015 | D13: 1 | E13: 15.92 | F13: East | G13: =UPPER(TRIM(C13)) -> P015 | H13: =IF(ISNUMBER(MATCH(G13,Products!$A$5:$A$24,0)),"OK","Mismatch") -> OK | I13: =IF(COUNTIF($A$5:A13,A13)>1,"Duplicate","Unique") -> Unique | J13: =IF(I13="Duplicate","Remove",IF(H13="Mismatch","Exclude","Keep")) -> Keep
A14: ORD-10010 | B14: 45659 | C14: P016 | D14: 2 | E14: 13.66 | F14: South | G14: =UPPER(TRIM(C14)) -> P016 | H14: =IF(ISNUMBER(MATCH(G14,Products!$A$5:$A$24,0)),"OK","Mismatch") -> OK | I14: =IF(COUNTIF($A$5:A14,A14)>1,"Duplicate","Unique") -> Unique | J14: =IF(I14="Duplicate","Remove",IF(H14="Mismatch","Exclude","Keep")) -> Keep
A15: ORD-10011 | B15: 45660 | C15: P003 | D15: 1 | E15: 34.04 | F15: West | G15: =UPPER(TRIM(C15)) -> P003 | H15: =IF(ISNUMBER(MATCH(G15,Products!$A$5:$A$24,0)),"OK","Mismatch") -> OK | I15: =IF(COUNTIF($A$5:A15,A15)>1,"Duplicate","Unique") -> Unique | J15: =IF(I15="Duplicate","Remove",IF(H15="Mismatch","Exclude","Keep")) -> Keep
A16: ORD-10012 | B16: 45660 | C16: P001 | D16: 1 | E16: 23.2 | F16: South | G16: =UPPER(TRIM(C16)) -> P001 | H16: =IF(ISNUMBER(MATCH(G16,Products!$A$5:$A$24,0)),"OK","Mismatch") -> OK | I16: =IF(COUNTIF($A$5:A16,A16)>1,"Duplicate","Unique") -> Unique | J16: =IF(I16="Duplicate","Remove",IF(H16="Mismatch","Exclude","Keep")) -> Keep
... A3074: ORD-13000 | B3074: 46019 | C3074: P011 | D3074: 2 | E3074: 8.91 | F3074: South | G3074: =UPPER(TRIM(C3074)) -> P011 | H3074: =IF(ISNUMBER(MATCH(G3074,Products!$A$5:$A$24,0)),"OK","Mismatch") -> OK | I3074: =IF(COUNTIF($A$5:A3074,A3074)>1,"Duplicate","Unique") -> Unique | J3074: =IF(I3074="Duplicate","Remove",IF(H3074="Mismatch","Exclude","Keep")) -> Keep

Sheet Raw_Expenses
A1: Raw Expense Records (as received)
A2: One expense record per order: Shipping, Marketing, Packaging or Platform Fees.
A4: Order ID | B4: Expense Type | C4: Expense Amount
A5: ORD-10945 | B5: Platform Fees | C5: 17.89
A6: ORD-10367 | B6: Shipping | C6: 1.02
A7: ORD-11928 | B7: Platform Fees | C7: 23.44
A8: ORD-10171 | B8: Packaging | C8: 47.76
A9: ORD-12968 | B9: Shipping | C9: 16.96
A10: ORD-10972 | B10: Marketing | C10: 0.74
A11: ORD-10584 | B11: Platform Fees | C11: 2.44
A12: ORD-10909 | B12: Packaging | C12: 0.64
A13: ORD-10310 | B13: Marketing | C13: 11.37
A14: ORD-12411 | B14: Shipping | C14: 4.07
A15: ORD-10192 | B15: Shipping | C15: 5.45
A16: ORD-11378 | B16: Marketing | C16: 4.54
... A2979: ORD-11534 | B2979: Platform Fees | C2979: 3.17

Sheet Products
A1: Product Master
A2: Lookup table used by VLOOKUP / INDEX-MATCH. Unit costs are inputs (blue).
A4: Product ID | B4: Product Name | C4: Category | D4: Unit Cost | E4: List Price
A5: P001 | B5: Wireless Mouse | C5: Electronics | D5: 12 | E5: 25
A6: P002 | B6: Mechanical Keyboard | C6: Electronics | D6: 38 | E6: 79
A7: P003 | B7: USB-C Hub | C7: Electronics | D7: 14 | E7: 35
A8: P004 | B8: Laptop Stand | C8: Accessories | D8: 11 | E8: 29
A9: P005 | B9: HD Webcam | C9: Electronics | D9: 22 | E9: 55
A10: P006 | B10: Noise-Cancelling Headphones | C10: Electronics | D10: 55 | E10: 129
A11: P007 | B11: Office Chair | C11: Furniture | D11: 85 | E11: 189
A12: P008 | B12: Standing Desk | C12: Furniture | D12: 160 | E12: 349
A13: P009 | B13: Desk Lamp | C13: Furniture | D13: 13 | E13: 32
A14: P010 | B14: 24-inch Monitor | C14: Electronics | D14: 90 | E14: 179
A15: P011 | B15: Notebook Set | C15: Stationery | D15: 3 | E15: 9
A16: P012 | B16: Gel Pen Pack | C16: Stationery | D16: 2 | E16: 6
... A24: P020 | B24: Ergonomic Footrest | C24: Furniture | D24: 15 | E24: 39
